odoo/addons/l10n_nl_partner_name/README.rst
odoo/addons/l10n_nl_partner_name/__init__.py
odoo/addons/l10n_nl_partner_name/__manifest__.py
odoo/addons/l10n_nl_partner_name/data/ir.config_parameter.xml
odoo/addons/l10n_nl_partner_name/i18n/l10n_nl_partner_name.pot
odoo/addons/l10n_nl_partner_name/i18n/nl.po
odoo/addons/l10n_nl_partner_name/models/__init__.py
odoo/addons/l10n_nl_partner_name/models/res_partner.py
odoo/addons/l10n_nl_partner_name/readme/CONFIGURE.md
odoo/addons/l10n_nl_partner_name/readme/CONTRIBUTORS.md
odoo/addons/l10n_nl_partner_name/readme/DESCRIPTION.md
odoo/addons/l10n_nl_partner_name/readme/ROADMAP.md
odoo/addons/l10n_nl_partner_name/static/description/icon.png
odoo/addons/l10n_nl_partner_name/static/description/index.html
odoo/addons/l10n_nl_partner_name/static/src/img/icon.png
odoo/addons/l10n_nl_partner_name/tests/__init__.py
odoo/addons/l10n_nl_partner_name/tests/test_l10n_nl_partner_name.py
odoo/addons/l10n_nl_partner_name/views/res_partner.xml
odoo_addon_l10n_nl_partner_name-17.0.1.0.0.2.dist-info/METADATA
odoo_addon_l10n_nl_partner_name-17.0.1.0.0.2.dist-info/WHEEL
odoo_addon_l10n_nl_partner_name-17.0.1.0.0.2.dist-info/top_level.txt
odoo_addon_l10n_nl_partner_name-17.0.1.0.0.2.dist-info/RECORD
