Metadata-Version: 2.1
Name: odoo-addon-l10n_nl_partner_name
Version: 17.0.1.0.0.2
Requires-Python: >=3.10
Requires-Dist: odoo-addon-partner_firstname>=17.0dev,<17.1dev
Requires-Dist: odoo>=17.0a,<17.1dev
Summary: Adapt parter names to Dutch conventions (support infix)
Home-page: https://github.com/OCA/l10n-netherlands
License: AGPL-3
Author: Hunki Enterprises BV, Therp BV, Odoo Community Association (OCA)
Author-email: support@odoo-community.org
Classifier: Programming Language :: Python
Classifier: Framework :: Odoo
Classifier: Framework :: Odoo :: 17.0
Classifier: License :: OSI Approved :: GNU Affero General Public License v3
